cl_forge/__init__.py
cl_forge/cmf.py
cl_forge/cmf.pyi
cl_forge/core/__init__.py
cl_forge/core/endpoints.py
cl_forge/core/impl/__init__.py
cl_forge/core/impl/_rs_cl_forge.cpython-314-darwin.so
cl_forge/core/impl/rs_cmf.py
cl_forge/core/impl/rs_exceptions.py
cl_forge/core/impl/rs_verify.py
cl_forge/core/schemas.py
cl_forge/core/timing.py
cl_forge/exceptions.py
cl_forge/exceptions.pyi
cl_forge/py.typed
cl_forge/utils.py
cl_forge/verify.py
cl_forge/verify.pyi
cl_forge-0.5.1.dist-info/METADATA
cl_forge-0.5.1.dist-info/WHEEL
cl_forge-0.5.1.dist-info/licenses/LICENSE
cl_forge-0.5.1.dist-info/RECORD
