Metadata-Version: 2.4
Name: cl-forge
Version: 0.5.1
Classifier: Development Status :: 3 - Alpha
Classifier: Intended Audience :: Developers
Classifier: License :: OSI Approved :: Apache Software License
Classifier: Operating System :: MacOS
Classifier: Operating System :: POSIX :: Linux
Classifier: Operating System :: Microsoft :: Windows
Classifier: Programming Language :: Python :: 3 :: Only
Classifier: Programming Language :: Python :: 3.14
Classifier: Programming Language :: Python :: 3.13
Classifier: Programming Language :: Python :: 3.12
Classifier: Programming Language :: Python
Classifier: Programming Language :: Rust
Classifier: Typing :: Typed
Classifier: Topic :: Utilities
Classifier: Topic :: Software Development :: Libraries
Requires-Dist: pydantic>=2.12.5
License-File: LICENSE
Summary: Simple yet powerful Chilean and other tools written in Rust and Python.
Keywords: chile,cl,utils,tools,rut,run,validators,api,python,rust
Author-email: Matías Schiaffino Tyrer <matias.scht@gmail.com>
Requires-Python: >=3.12
Project-URL: Homepage, https://github.com/mschiaff/cl-forge
Project-URL: Issues, https://github.com/mschiaff/cl-forge/issues
Project-URL: Repository, https://github.com/mschiaff/cl-forge.git
